drsip_common/__init__.py
drsip_common-0.5.dist-info/METADATA
drsip_common-0.5.dist-info/RECORD
drsip_common-0.5.dist-info/WHEEL
drsip_common-0.5.dist-info/top_level.txt
